rlx_helpers/__init__.py
rlx_helpers/adls_utils.py
rlx_helpers/azure_auth.py
rlx_helpers/graph_api.py
rlx_helpers/service_principal.py
rlx_helpers/sql_utils.py
rlx_helpers-0.1.0.dist-info/WHEEL
rlx_helpers-0.1.0.dist-info/METADATA
rlx_helpers-0.1.0.dist-info/RECORD
