Metadata-Version: 2.3
Name: rlx-helpers
Version: 0.1.0
Summary: A series of helper modules and classes for working with: Service Principals, Graph API, AzureSQL databases, Azure Data Lake Storage, Azure Keyvault
Requires-Dist: azure-identity>=1.23.0
Requires-Dist: azure-keyvault>=4.2.0
Requires-Dist: azure-storage-file-datalake>=12.20.0
Requires-Dist: requests>=2.32.3
Requires-Dist: sqlalchemy>=2.0.41
Requires-Python: >=3.9
